__init__.py
omicsone_meta/__init__.py
omicsone_meta/main.py
omicsone_meta/plugins/meta.cp39-win_amd64.pyd
omicsone_meta/plugins/param.cp39-win_amd64.pyd
omicsone_meta-0.1.2.dist-info/LICENSE
omicsone_meta-0.1.2.dist-info/METADATA
omicsone_meta-0.1.2.dist-info/WHEEL
omicsone_meta-0.1.2.dist-info/entry_points.txt
omicsone_meta-0.1.2.dist-info/top_level.txt
omicsone_meta-0.1.2.dist-info/RECORD
